contact_form/__init__.py
contact_form/akismet_urls.py
contact_form/forms.py
contact_form/recaptcha_urls.py
contact_form/runtests.py
contact_form/urls.py
contact_form/views.py
contact_form/locale/de/LC_MESSAGES/django.mo
contact_form/locale/de/LC_MESSAGES/django.po
contact_form/locale/en/LC_MESSAGES/django.mo
contact_form/locale/en/LC_MESSAGES/django.po
contact_form/locale/es/LC_MESSAGES/django.mo
contact_form/locale/es/LC_MESSAGES/django.po
contact_form/locale/es_AR/LC_MESSAGES/django.mo
contact_form/locale/es_AR/LC_MESSAGES/django.po
contact_form/locale/eu/LC_MESSAGES/django.mo
contact_form/locale/eu/LC_MESSAGES/django.po
contact_form/locale/fr/LC_MESSAGES/django.mo
contact_form/locale/fr/LC_MESSAGES/django.po
contact_form/templates/contact_form/contact_form.html
contact_form/templates/contact_form/contact_form.txt
contact_form/templates/contact_form/contact_form_sent.html
contact_form/templates/contact_form/contact_form_subject.txt
contact_form/tests/__init__.py
contact_form/tests/test_forms.py
contact_form/tests/test_urls.py
contact_form/tests/test_views.py
django_contact_form_recaptcha-1.6.1.dist-info/LICENSE
django_contact_form_recaptcha-1.6.1.dist-info/METADATA
django_contact_form_recaptcha-1.6.1.dist-info/WHEEL
django_contact_form_recaptcha-1.6.1.dist-info/top_level.txt
django_contact_form_recaptcha-1.6.1.dist-info/RECORD
