Metadata-Version: 2.1
Name: django-contact-form-recaptcha
Version: 1.6.1
Summary: A generic contact-form application for Django
Home-page: https://github.com/maru/django-contact-form-recaptcha/
Author: James Bennett, Maru Berezin
License: UNKNOWN
Platform: UNKNOWN
Classifier: Development Status :: 5 - Production/Stable
Classifier: Environment :: Web Environment
Classifier: Framework :: Django
Classifier: Framework :: Django :: 1.11
Classifier: Framework :: Django :: 2.0
Classifier: Intended Audience :: Developers
Classifier: License :: OSI Approved :: BSD License
Classifier: Operating System :: OS Independent
Classifier: Programming Language :: Python
Classifier: Programming Language :: Python :: 2
Classifier: Programming Language :: Python :: 2.7
Classifier: Programming Language :: Python :: 3
Classifier: Programming Language :: Python :: 3.4
Classifier: Programming Language :: Python :: 3.5
Classifier: Programming Language :: Python :: 3.6
Classifier: Topic :: Utilities
Requires-Dist: Django (>=1.11)
Requires-Dist: django-recaptcha
Provides-Extra: akismet
Requires-Dist: akismet ; extra == 'akismet'
